sagemath_objects-10.5.dist-info/top_level.txt
sagemath_objects-10.5.dist-info/RECORD
sagemath_objects-10.5.dist-info/METADATA
sagemath_objects-10.5.dist-info/WHEEL
sagemath_objects.libs/libgmp-5d826a90.so.10.5.0
sage/all__sagemath_objects.py
sage/sets/pythonclass.pxd
sage/sets/all__sagemath_objects.py
sage/sets/pythonclass.pyx
sage/sets/pythonclass.cpython-312-x86_64-linux-musl.so
sage/categories/primer.py
sage/categories/isomorphic_objects.py
sage/categories/functor.pyx
sage/categories/subobjects.py
sage/categories/category_singleton.cpython-312-x86_64-linux-musl.so
sage/categories/map.pyx
sage/categories/map.pxd
sage/categories/cartesian_product.py
sage/categories/with_realizations.py
sage/categories/action.cpython-312-x86_64-linux-musl.so
sage/categories/category_with_axiom.py
sage/categories/category_cy_helper.pyx
sage/categories/quotients.py
sage/categories/objects.py
sage/categories/functor.pxd
sage/categories/category_cy_helper.pxd
sage/categories/action.pyx
sage/categories/morphism.cpython-312-x86_64-linux-musl.so
sage/categories/basic.py
sage/categories/sets_cat.py
sage/categories/realizations.py
sage/categories/functor.cpython-312-x86_64-linux-musl.so
sage/categories/algebra_functor.py
sage/categories/category_singleton.pyx
sage/categories/category.py
sage/categories/pushout.py
sage/categories/homset.py
sage/categories/morphism.pxd
sage/categories/all__sagemath_objects.py
sage/categories/facade_sets.py
sage/categories/action.pxd
sage/categories/map.cpython-312-x86_64-linux-musl.so
sage/categories/covariant_functorial_construction.py
sage/categories/subquotients.py
sage/categories/homsets.py
sage/categories/category_cy_helper.cpython-312-x86_64-linux-musl.so
sage/categories/sets_with_partial_maps.py
sage/categories/category_types.py
sage/categories/morphism.pyx
sage/categories/category_singleton.pxd
sage/libs/all__sagemath_objects.py
sage/libs/gmp/mpz.pxd
sage/libs/gmp/pylong.pyx
sage/libs/gmp/misc.pxd
sage/libs/gmp/random.pxd
sage/libs/gmp/pylong.pxd
sage/libs/gmp/mpn.pxd
sage/libs/gmp/__init__.py
sage/libs/gmp/randomize.pxd
sage/libs/gmp/mpq.pxd
