Metadata-Version: 2.1
Name: sagemath-objects
Version: 10.5
Summary: Sage: Open Source Mathematics Software: Sage objects, elements, parents, categories, coercion, metaclasses
Author-email: The Sage Developers <sage-support@googlegroups.com>
License: GNU General Public License (GPL) v2 or later
Project-URL: download, https://doc.sagemath.org/html/en/installation/index.html
Project-URL: release notes, https://github.com/sagemath/sage/releases
Project-URL: source, https://github.com/sagemath/sage
Project-URL: documentation, https://doc.sagemath.org
Project-URL: homepage, https://www.sagemath.org
Project-URL: tracker, https://github.com/sagemath/sage/issues
Classifier: Development Status :: 6 - Mature
Classifier: Intended Audience :: Education
Classifier: Intended Audience :: Science/Research
Classifier: License :: OSI Approved :: GNU General Public License v2 or later (GPLv2+)
Classifier: Operating System :: POSIX
Classifier: Operating System :: MacOS :: MacOS X
Classifier: Programming Language :: Python :: 3 :: Only
Classifier: Programming Language :: Python :: 3.9
Classifier: Programming Language :: Python :: 3.10
Classifier: Programming Language :: Python :: 3.11
Classifier: Programming Language :: Python :: 3.12
Classifier: Programming Language :: Python :: Implementation :: CPython
Classifier: Topic :: Scientific/Engineering :: Mathematics
Requires-Python: <3.13,>=3.9
Requires-Dist: gmpy2~=2.1.b999
Requires-Dist: cysignals>=1.10.2
Provides-Extra: test
